social_layer/__init__.py
social_layer/apps.py
social_layer/context_processor.py
social_layer/models.py
social_layer/signals.py
social_layer/tests.py
social_layer/urls.py
social_layer/utils.py
social_layer/__pycache__/__init__.cpython-39.pyc
social_layer/__pycache__/admin.cpython-39.pyc
social_layer/__pycache__/apps.cpython-39.pyc
social_layer/__pycache__/models.cpython-39.pyc
social_layer/__pycache__/signals.cpython-39.pyc
social_layer/__pycache__/tasks.cpython-39.pyc
social_layer/__pycache__/tests.cpython-39.pyc
social_layer/__pycache__/urls.cpython-39.pyc
social_layer/__pycache__/utils.cpython-39.pyc
social_layer/comments/__init__.py
social_layer/comments/admin.py
social_layer/comments/apps.py
social_layer/comments/forms.py
social_layer/comments/models.py
social_layer/comments/tests.py
social_layer/comments/urls.py
social_layer/comments/utils.py
social_layer/comments/views.py
social_layer/comments/__pycache__/__init__.cpython-39.pyc
social_layer/comments/__pycache__/forms.cpython-39.pyc
social_layer/comments/__pycache__/models.cpython-39.pyc
social_layer/comments/__pycache__/tests.cpython-39.pyc
social_layer/comments/__pycache__/urls.cpython-39.pyc
social_layer/comments/__pycache__/utils.cpython-39.pyc
social_layer/comments/__pycache__/views.cpython-39.pyc
social_layer/comments/migrations/__init__.py
social_layer/comments/migrations/__pycache__/__init__.cpython-39.pyc
social_layer/locale/pt/LC_MESSAGES/django.mo
social_layer/locale/pt/LC_MESSAGES/django.po
social_layer/management/__init__.py
social_layer/management/__pycache__/__init__.cpython-39.pyc
social_layer/management/commands/__init__.py
social_layer/management/commands/__pycache__/__init__.cpython-39.pyc
social_layer/management/commands/__pycache__/sl_format_media.cpython-39.pyc
social_layer/mediautils/__init__.py
social_layer/mediautils/apps.py
social_layer/mediautils/models.py
social_layer/mediautils/tasks.py
social_layer/mediautils/tests.py
social_layer/mediautils/urls.py
django_social_layer-1.0.2.dist-info/LICENSE
django_social_layer-1.0.2.dist-info/METADATA
django_social_layer-1.0.2.dist-info/WHEEL
django_social_layer-1.0.2.dist-info/top_level.txt
django_social_layer-1.0.2.dist-info/RECORD
