Metadata-Version: 2.1
Name: django-social-layer
Version: 1.0.2
Summary: Adds social media features to any website
Home-page: https://github.com/gsteixeira
Author: Gustavo Selbach Teixeira
Author-email: gsteixei@gmail.com
License: GNU License
Classifier: Environment :: Web Environment
Classifier: Framework :: Django
License-File: LICENSE
Requires-Dist: Django >=2.2.0
Requires-Dist: Pillow >=8.4.0
Requires-Dist: opencv-python >=4.5.5.64
Requires-Dist: django-infinite-scroll >=0.1.7
Requires-Dist: celery >=5.2.3
